<?xml version="1.0" encoding="UTF-8" standalone="no"?>
<databaseChangeLog xmlns="http://www.liquibase.org/xml/ns/dbchangelog/1.9" xmlns:xsi="http://www.w3.org/2001/XMLSchema-instance" xsi:schemaLocation="http://www.liquibase.org/xml/ns/dbchangelog/1.9 http://www.liquibase.org/xml/ns/dbchangelog/dbchangelog-1.9.xsd">

<changeSet author="thickerson" id="2010-10-05-5556-1" dbms="postgresql">
		<comment>Change data type of created_date to timestamp</comment>
		<sql>ALTER TABLE archived_dataset_file alter column date_created TYPE timestamp(6) using cast (date_created as timestamp)</sql>
		<rollback>
		  <sql></sql>
		</rollback>
	</changeSet>
</databaseChangeLog>